{
  "id": 460,
  "name": "Abomasnow",
  "dexNum": 460,
  "forms": [
    {
      "name": "Abomasnow",
      "formName": "Default Form",
      "formIndex": 0,
      "abilities": [
        "Snow Warning",
        "Soundproof"
      ],
      "moves": [
        "Mega Punch",
        "Ice Punch",
        "Swords Dance",
        "Stomp",
        "Mega Kick",
        "Double-Edge",
        "Leer",
        "Mist",
        "Ice Beam",
        "Blizzard",
        "Hyper Beam",
        "Leech Seed",
        "Growth",
        "Razor Leaf",
        "Solar Beam",
        "Earthquake",
        "Light Screen",
        "Skull Bash",
        "Rest",
        "Rock Slide",
        "Substitute",
        "Snore",
        "Powder Snow",
        "Protect",
        "Icy Wind",
        "Outrage",
        "Giga Drain",
        "Endure",
        "Swagger",
        "Attract",
        "Sleep Talk",
        "Safeguard",
        "Iron Tail",
        "Rain Dance",
        "Shadow Ball",
        "Hail",
        "Facade",
        "Ingrain",
        "Brick Break",
        "Weather Ball",
        "Rock Tomb",
        "Sheer Cold",
        "Bullet Seed",
        "Icicle Spear",
        "Magical Leaf",
        "Fling",
        "Seed Bomb",
        "Focus Blast",
        "Energy Ball",
        "Earth Power",
        "Giga Impact",
        "Avalanche",
        "Ice Shard",
        "Leaf Storm",
        "Grass Knot",
        "Wood Hammer",
        "Round",
        "Bulldoze",
        "Leafage",
        "Aurora Veil",
        "Stomping Tantrum",
        "Grassy Glide"
      ],
      "canShiny": true,
      "canAlpha": false,
      "canAlphaShiny": false,
      "canGigantamax": false,
      "levelMax": 65,
      "spriteNormal": "sprites/poke_capture_0460_000_fd_n_00000000_f_n.png",
      "spriteShiny": "sprites/poke_capture_0460_000_fd_n_00000000_f_r.png",
      "spriteGmax": "",
      "spriteShinyGmax": ""
    }
  ]
}