{
  "id": 582,
  "name": "Vanillite",
  "dexNum": 582,
  "forms": [
    {
      "name": "Vanillite",
      "formName": "Default Form",
      "formIndex": 0,
      "abilities": [
        "Ice Body",
        "Snow Cloak",
        "Weak Armor"
      ],
      "moves": [
        "Mist",
        "Ice Beam",
        "Blizzard",
        "Harden",
        "Light Screen",
        "Self-Destruct",
        "Acid Armor",
        "Explosion",
        "Rest",
        "Substitute",
        "Snore",
        "Protect",
        "Icy Wind",
        "Endure",
        "Attract",
        "Sleep Talk",
        "Rain Dance",
        "Mirror Coat",
        "Uproar",
        "Hail",
        "Facade",
        "Taunt",
        "Imprison",
        "Hyper Voice",
        "Astonish",
        "Sheer Cold",
        "Icicle Spear",
        "Iron Defense",
        "Magnet Rise",
        "Avalanche",
        "Ice Shard",
        "Flash Cannon",
        "Autotomize",
        "Round",
        "Ally Switch",
        "Icicle Crash",
        "Aurora Veil"
      ],
      "canShiny": true,
      "canAlpha": false,
      "canAlphaShiny": false,
      "canGigantamax": false,
      "levelMax": 65,
      "spriteNormal": "sprites/poke_capture_0582_000_mf_n_00000000_f_n.png",
      "spriteShiny": "sprites/poke_capture_0582_000_mf_n_00000000_f_r.png",
      "spriteGmax": "",
      "spriteShinyGmax": ""
    }
  ]
}