{
  "id": 614,
  "name": "Beartic",
  "dexNum": 614,
  "forms": [
    {
      "name": "Beartic",
      "formName": "Default Form",
      "formIndex": 0,
      "abilities": [
        "Snow Cloak",
        "Slush Rush",
        "Swift Swim"
      ],
      "moves": [
        "Mega Punch",
        "Ice Punch",
        "Swords Dance",
        "Mega Kick",
        "Thrash",
        "Growl",
        "Surf",
        "Ice Beam",
        "Blizzard",
        "Hyper Beam",
        "Low Kick",
        "Dig",
        "Fury Swipes",
        "Rest",
        "Rock Slide",
        "Slash",
        "Substitute",
        "Snore",
        "Flail",
        "Powder Snow",
        "Protect",
        "Scary Face",
        "Icy Wind",
        "Endure",
        "Charm",
        "Swagger",
        "Attract",
        "Sleep Talk",
        "Encore",
        "Rain Dance",
        "Hail",
        "Facade",
        "Focus Punch",
        "Taunt",
        "Superpower",
        "Brick Break",
        "Yawn",
        "Dive",
        "Rock Tomb",
        "Sheer Cold",
        "Icicle Spear",
        "Bulk Up",
        "Brine",
        "Assurance",
        "Fling",
        "Night Slash",
        "Focus Blast",
        "Giga Impact",
        "Avalanche",
        "Shadow Claw",
        "Ice Fang",
        "Stone Edge",
        "Grass Knot",
        "Aqua Jet",
        "Heavy Slam",
        "Round",
        "Bulldoze",
        "Frost Breath",
        "Icicle Crash",
        "Play Rough",
        "Play Nice",
        "Throat Chop",
        "Liquidation",
        "Body Press"
      ],
      "canShiny": true,
      "canAlpha": false,
      "canAlphaShiny": false,
      "canGigantamax": false,
      "levelMax": 67,
      "spriteNormal": "sprites/poke_capture_0614_000_mf_n_00000000_f_n.png",
      "spriteShiny": "sprites/poke_capture_0614_000_mf_n_00000000_f_r.png",
      "spriteGmax": "",
      "spriteShinyGmax": ""
    }
  ]
}