{
  "id": 713,
  "name": "Avalugg",
  "dexNum": 713,
  "forms": [
    {
      "name": "Avalugg",
      "formName": "Default Form",
      "formIndex": 0,
      "abilities": [
        "Own Tempo",
        "Ice Body",
        "Sturdy"
      ],
      "moves": [
        "Tackle",
        "Body Slam",
        "Take Down",
        "Double-Edge",
        "Bite",
        "Mist",
        "Hydro Pump",
        "Surf",
        "Ice Beam",
        "Blizzard",
        "Hyper Beam",
        "Earthquake",
        "Recover",
        "Harden",
        "Skull Bash",
        "Rest",
        "Rock Slide",
        "Substitute",
        "Snore",
        "Curse",
        "Powder Snow",
        "Protect",
        "Icy Wind",
        "Endure",
        "Attract",
        "Sleep Talk",
        "Safeguard",
        "Rapid Spin",
        "Rain Dance",
        "Crunch",
        "Mirror Coat",
        "Hail",
        "Facade",
        "Superpower",
        "Rock Tomb",
        "Icicle Spear",
        "Iron Defense",
        "Gyro Ball",
        "Giga Impact",
        "Avalanche",
        "Ice Fang",
        "Flash Cannon",
        "Iron Head",
        "Stone Edge",
        "Wide Guard",
        "Heavy Slam",
        "Round",
        "Bulldoze",
        "High Horsepower",
        "Aurora Veil",
        "Stomping Tantrum",
        "Body Press"
      ],
      "canShiny": true,
      "canAlpha": false,
      "canAlphaShiny": false,
      "canGigantamax": false,
      "levelMax": 65,
      "spriteNormal": "sprites/poke_capture_0713_000_mf_n_00000000_f_n.png",
      "spriteShiny": "sprites/poke_capture_0713_000_mf_n_00000000_f_r.png",
      "spriteGmax": "",
      "spriteShinyGmax": ""
    }
  ]
}