{
  "id": 878,
  "name": "Cufant",
  "dexNum": 878,
  "forms": [
    {
      "name": "Cufant",
      "formName": "Default Form",
      "formIndex": 0,
      "abilities": [
        "Sheer Force",
        "Heavy Metal"
      ],
      "moves": [
        "Whirlwind",
        "Slam",
        "Stomp",
        "Mega Kick",
        "Tackle",
        "Body Slam",
        "Double-Edge",
        "Growl",
        "Strength",
        "Fissure",
        "Dig",
        "Screech",
        "Defense Curl",
        "Rest",
        "Rock Slide",
        "Substitute",
        "Snore",
        "Curse",
        "Protect",
        "Endure",
        "Rollout",
        "Swagger",
        "Attract",
        "Sleep Talk",
        "Rock Smash",
        "Facade",
        "Superpower",
        "Brick Break",
        "Rock Tomb",
        "Iron Defense",
        "Mud Shot",
        "Rock Blast",
        "Fling",
        "Earth Power",
        "Zen Headbutt",
        "Power Whip",
        "Iron Head",
        "Stealth Rock",
        "Round",
        "Bulldoze",
        "Work Up",
        "Belch",
        "Play Rough",
        "High Horsepower",
        "Brutal Swing",
        "Stomping Tantrum",
        "Body Press",
        "Steel Beam",
        "Steel Roller"
      ],
      "canShiny": true,
      "canAlpha": false,
      "canAlphaShiny": false,
      "canGigantamax": false,
      "levelMax": 65,
      "spriteNormal": "sprites/poke_capture_0878_000_mf_n_00000000_f_n.png",
      "spriteShiny": "sprites/poke_capture_0878_000_mf_n_00000000_f_r.png",
      "spriteGmax": "",
      "spriteShinyGmax": ""
    }
  ]
}