{
  "id": 217,
  "name": "Ursaring",
  "dexNum": 217,
  "forms": [
    {
      "name": "Ursaring",
      "formName": "Default Form",
      "formIndex": 0,
      "abilities": [
        "Guts",
        "Quick Feet",
        "Unnerve"
      ],
      "moves": [
        "Fire Punch",
        "Ice Punch",
        "Thunder Punch",
        "Scratch",
        "Swords Dance",
        "Body Slam",
        "Take Down",
        "Thrash",
        "Double-Edge",
        "Leer",
        "Hyper Beam",
        "Low Kick",
        "Counter",
        "Seismic Toss",
        "Earthquake",
        "Dig",
        "Metronome",
        "Lick",
        "Swift",
        "Fury Swipes",
        "Rest",
        "Rock Slide",
        "Slash",
        "Substitute",
        "Thief",
        "Snore",
        "Protect",
        "Scary Face",
        "Belly Drum",
        "Endure",
        "Charm",
        "Fury Cutter",
        "Sleep Talk",
        "Sweet Scent",
        "Metal Claw",
        "Cross Chop",
        "Rain Dance",
        "Sunny Day",
        "Crunch",
        "Uproar",
        "Facade",
        "Focus Punch",
        "Taunt",
        "Helping Hand",
        "Brick Break",
        "Yawn",
        "Hyper Voice",
        "Fake Tears",
        "Rock Tomb",
        "Aerial Ace",
        "Bulk Up",
        "Covet",
        "Hammer Arm",
        "Close Combat",
        "Payback",
        "Fling",
        "Night Slash",
        "Seed Bomb",
        "Giga Impact",
        "Avalanche",
        "Shadow Claw",
        "Gunk Shot",
        "Stone Edge",
        "Smack Down",
        "Bulldoze",
        "Play Rough",
        "Play Nice",
        "Baby-Doll Eyes",
        "High Horsepower",
        "Throat Chop",
        "Stomping Tantrum",
        "Tera Blast",
        "Trailblaze"
      ],
      "canShiny": true,
      "canAlpha": false,
      "canAlphaShiny": false,
      "canGigantamax": false,
      "levelMax": 53,
      "spriteNormal": "sprites/poke_capture_0217_000_md_n_00000000_f_n.png",
      "spriteShiny": "sprites/poke_capture_0217_000_md_n_00000000_f_r.png",
      "spriteGmax": "",
      "spriteShinyGmax": ""
    }
  ]
}