{
  "id": 370,
  "name": "Luvdisc",
  "dexNum": 370,
  "forms": [
    {
      "name": "Luvdisc",
      "formName": "Default Form",
      "formIndex": 0,
      "abilities": [
        "Swift Swim",
        "Hydration"
      ],
      "moves": [
        "Tackle",
        "Take Down",
        "Supersonic",
        "Water Gun",
        "Hydro Pump",
        "Surf",
        "Ice Beam",
        "Blizzard",
        "Agility",
        "Waterfall",
        "Splash",
        "Rest",
        "Substitute",
        "Flail",
        "Protect",
        "Sweet Kiss",
        "Icy Wind",
        "Endure",
        "Charm",
        "Attract",
        "Sleep Talk",
        "Safeguard",
        "Rain Dance",
        "Psych Up",
        "Whirlpool",
        "Facade",
        "Wish",
        "Endeavor",
        "Water Pulse",
        "Aqua Ring",
        "Aqua Jet",
        "Soak",
        "Entrainment",
        "Draining Kiss",
        "Baby-Doll Eyes",
        "Liquidation",
        "Scale Shot",
        "Flip Turn",
        "Tera Blast",
        "Snowscape"
      ],
      "canShiny": true,
      "canAlpha": false,
      "canAlphaShiny": false,
      "canGigantamax": false,
      "levelMax": 75,
      "spriteNormal": "sprites/poke_capture_0370_000_mf_n_00000000_f_n.png",
      "spriteShiny": "sprites/poke_capture_0370_000_mf_n_00000000_f_r.png",
      "spriteGmax": "",
      "spriteShinyGmax": ""
    }
  ]
}