{
  "id": 402,
  "name": "Kricketune",
  "dexNum": 402,
  "forms": [
    {
      "name": "Kricketune",
      "formName": "Default Form",
      "formIndex": 0,
      "abilities": [
        "Swarm",
        "Technician"
      ],
      "moves": [
        "Swords Dance",
        "Tackle",
        "Take Down",
        "Growl",
        "Sing",
        "Hyper Beam",
        "Absorb",
        "Screech",
        "Focus Energy",
        "Leech Life",
        "Rest",
        "Slash",
        "Substitute",
        "Protect",
        "Perish Song",
        "Giga Drain",
        "Endure",
        "False Swipe",
        "Fury Cutter",
        "Sleep Talk",
        "Baton Pass",
        "Rain Dance",
        "Sunny Day",
        "Uproar",
        "Facade",
        "Taunt",
        "Helping Hand",
        "Brick Break",
        "Knock Off",
        "Endeavor",
        "Hyper Voice",
        "Aerial Ace",
        "Night Slash",
        "X-Scissor",
        "Bug Buzz",
        "Giga Impact",
        "Bug Bite",
        "Struggle Bug",
        "Sticky Web",
        "Fell Stinger",
        "Throat Chop",
        "Lunge",
        "Skitter Smack",
        "Tera Blast",
        "Pounce",
        "Trailblaze"
      ],
      "canShiny": true,
      "canAlpha": false,
      "canAlphaShiny": false,
      "canGigantamax": false,
      "levelMax": 68,
      "spriteNormal": "sprites/poke_capture_0402_000_md_n_00000000_f_n.png",
      "spriteShiny": "sprites/poke_capture_0402_000_md_n_00000000_f_r.png",
      "spriteGmax": "",
      "spriteShinyGmax": ""
    }
  ]
}