{
  "id": 478,
  "name": "Froslass",
  "dexNum": 478,
  "forms": [
    {
      "name": "Froslass",
      "formName": "Default Form",
      "formIndex": 0,
      "abilities": [
        "Snow Cloak",
        "Cursed Body"
      ],
      "moves": [
        "Ice Punch",
        "Headbutt",
        "Body Slam",
        "Take Down",
        "Leer",
        "Bite",
        "Disable",
        "Ice Beam",
        "Blizzard",
        "Hyper Beam",
        "Thunderbolt",
        "Thunder Wave",
        "Thunder",
        "Psychic",
        "Night Shade",
        "Double Team",
        "Confuse Ray",
        "Light Screen",
        "Haze",
        "Reflect",
        "Rest",
        "Substitute",
        "Curse",
        "Spite",
        "Powder Snow",
        "Protect",
        "Scary Face",
        "Spikes",
        "Destiny Bond",
        "Icy Wind",
        "Endure",
        "Charm",
        "Rollout",
        "Sleep Talk",
        "Pain Split",
        "Rain Dance",
        "Crunch",
        "Psych Up",
        "Shadow Ball",
        "Will-O-Wisp",
        "Facade",
        "Taunt",
        "Helping Hand",
        "Trick",
        "Imprison",
        "Astonish",
        "Weather Ball",
        "Fake Tears",
        "Icicle Spear",
        "Block",
        "Water Pulse",
        "Fling",
        "Switcheroo",
        "Giga Impact",
        "Avalanche",
        "Ice Shard",
        "Ice Fang",
        "Hex",
        "Frost Breath",
        "Icicle Crash",
        "Draining Kiss",
        "Aurora Veil",
        "Poltergeist",
        "Triple Axel",
        "Tera Blast",
        "Ice Spinner",
        "Snowscape",
        "Trailblaze",
        "Chilling Water"
      ],
      "canShiny": true,
      "canAlpha": false,
      "canAlphaShiny": false,
      "canGigantamax": false,
      "levelMax": 82,
      "spriteNormal": "sprites/poke_capture_0478_000_fo_n_00000000_f_n.png",
      "spriteShiny": "sprites/poke_capture_0478_000_fo_n_00000000_f_r.png",
      "spriteGmax": "",
      "spriteShinyGmax": ""
    }
  ]
}