{
  "id": 572,
  "name": "Minccino",
  "dexNum": 572,
  "forms": [
    {
      "name": "Minccino",
      "formName": "Default Form",
      "formIndex": 0,
      "abilities": [
        "Cute Charm",
        "Technician",
        "Skill Link"
      ],
      "moves": [
        "Pound",
        "Slam",
        "Take Down",
        "Tail Whip",
        "Sing",
        "Thunderbolt",
        "Thunder Wave",
        "Dig",
        "Swift",
        "Rest",
        "Super Fang",
        "Substitute",
        "Thief",
        "Flail",
        "Protect",
        "Mud-Slap",
        "Endure",
        "Charm",
        "Sleep Talk",
        "Baton Pass",
        "Encore",
        "Rain Dance",
        "Sunny Day",
        "Uproar",
        "Facade",
        "Helping Hand",
        "Knock Off",
        "Endeavor",
        "Hyper Voice",
        "Fake Tears",
        "Tickle",
        "Bullet Seed",
        "Calm Mind",
        "U-turn",
        "Fling",
        "Last Resort",
        "Aqua Tail",
        "Seed Bomb",
        "Gunk Shot",
        "Grass Knot",
        "After You",
        "Echoed Voice",
        "Tail Slap",
        "Play Rough",
        "Dazzling Gleam",
        "Baby-Doll Eyes",
        "Triple Axel",
        "Tera Blast",
        "Tidy Up",
        "Trailblaze",
        "Chilling Water",
        "Alluring Voice"
      ],
      "canShiny": true,
      "canAlpha": false,
      "canAlphaShiny": false,
      "canGigantamax": false,
      "levelMax": 71,
      "spriteNormal": "sprites/poke_capture_0572_000_mf_n_00000000_f_n.png",
      "spriteShiny": "sprites/poke_capture_0572_000_mf_n_00000000_f_r.png",
      "spriteGmax": "",
      "spriteShinyGmax": ""
    }
  ]
}