{
  "id": 612,
  "name": "Haxorus",
  "dexNum": 612,
  "forms": [
    {
      "name": "Haxorus",
      "formName": "Default Form",
      "formIndex": 0,
      "abilities": [
        "Rivalry",
        "Mold Breaker",
        "Unnerve"
      ],
      "moves": [
        "Scratch",
        "Guillotine",
        "Swords Dance",
        "Body Slam",
        "Take Down",
        "Double-Edge",
        "Leer",
        "Bite",
        "Roar",
        "Surf",
        "Hyper Beam",
        "Low Kick",
        "Counter",
        "Earthquake",
        "Dig",
        "Focus Energy",
        "Swift",
        "Rest",
        "Rock Slide",
        "Slash",
        "Substitute",
        "Reversal",
        "Protect",
        "Scary Face",
        "Outrage",
        "Endure",
        "False Swipe",
        "Sleep Talk",
        "Iron Tail",
        "Rain Dance",
        "Sunny Day",
        "Crunch",
        "Facade",
        "Taunt",
        "Brick Break",
        "Endeavor",
        "Rock Tomb",
        "Aerial Ace",
        "Dragon Claw",
        "Dragon Dance",
        "Close Combat",
        "Assurance",
        "Fling",
        "Poison Jab",
        "Night Slash",
        "Aqua Tail",
        "X-Scissor",
        "Dragon Pulse",
        "Focus Blast",
        "Giga Impact",
        "Shadow Claw",
        "Draco Meteor",
        "Iron Head",
        "Grass Knot",
        "Low Sweep",
        "Bulldoze",
        "Dragon Tail",
        "Snarl",
        "First Impression",
        "Stomping Tantrum",
        "Breaking Swipe",
        "Scale Shot",
        "Tera Blast",
        "Trailblaze",
        "Dragon Cheer"
      ],
      "canShiny": true,
      "canAlpha": false,
      "canAlphaShiny": false,
      "canGigantamax": false,
      "levelMax": 75,
      "spriteNormal": "sprites/poke_capture_0612_000_mf_n_00000000_f_n.png",
      "spriteShiny": "sprites/poke_capture_0612_000_mf_n_00000000_f_r.png",
      "spriteGmax": "",
      "spriteShinyGmax": ""
    }
  ]
}