{
  "id": 849,
  "name": "Toxtricity",
  "dexNum": 849,
  "forms": [
    {
      "name": "Toxtricity",
      "formName": "Default Form",
      "formIndex": 0,
      "abilities": [
        "Punk Rock",
        "Plus",
        "Technician"
      ],
      "moves": [
        "Fire Punch",
        "Thunder Punch",
        "Take Down",
        "Leer",
        "Growl",
        "Acid",
        "Hyper Beam",
        "Thunder Shock",
        "Thunderbolt",
        "Thunder Wave",
        "Thunder",
        "Toxic",
        "Screech",
        "Metronome",
        "Swift",
        "Rest",
        "Substitute",
        "Thief",
        "Flail",
        "Protect",
        "Scary Face",
        "Sludge Bomb",
        "Endure",
        "Charm",
        "Swagger",
        "Spark",
        "Sleep Talk",
        "Encore",
        "Rain Dance",
        "Sunny Day",
        "Uproar",
        "Facade",
        "Charge",
        "Taunt",
        "Helping Hand",
        "Brick Break",
        "Endeavor",
        "Hyper Voice",
        "Metal Sound",
        "Poison Tail",
        "Shock Wave",
        "Fling",
        "Toxic Spikes",
        "Poison Jab",
        "Drain Punch",
        "Giga Impact",
        "Thunder Fang",
        "Discharge",
        "Gunk Shot",
        "Charge Beam",
        "Venoshock",
        "Sludge Wave",
        "Electro Ball",
        "Acid Spray",
        "Stored Power",
        "Hex",
        "Shift Gear",
        "Volt Switch",
        "Electroweb",
        "Wild Charge",
        "Snarl",
        "Belch",
        "Noble Roar",
        "Boomburst",
        "Eerie Impulse",
        "Electric Terrain",
        "Nuzzle",
        "Throat Chop",
        "Tearful Look",
        "Overdrive",
        "Tera Blast",
        "Trailblaze",
        "Psychic Noise"
      ],
      "canShiny": true,
      "canAlpha": false,
      "canAlphaShiny": false,
      "canGigantamax": false,
      "levelMax": 75,
      "spriteNormal": "sprites/poke_capture_0849_000_mf_n_00000000_f_n.png",
      "spriteShiny": "sprites/poke_capture_0849_000_mf_n_00000000_f_r.png",
      "spriteGmax": "",
      "spriteShinyGmax": ""
    },
    {
      "name": "Toxtricity",
      "formName": "Low Key",
      "formIndex": 1,
      "abilities": [
        "Punk Rock",
        "Minus",
        "Technician"
      ],
      "moves": [
        "Fire Punch",
        "Thunder Punch",
        "Take Down",
        "Leer",
        "Growl",
        "Acid",
        "Hyper Beam",
        "Thunder Shock",
        "Thunderbolt",
        "Thunder Wave",
        "Thunder",
        "Toxic",
        "Screech",
        "Metronome",
        "Swift",
        "Rest",
        "Substitute",
        "Thief",
        "Flail",
        "Protect",
        "Scary Face",
        "Sludge Bomb",
        "Endure",
        "Charm",
        "Swagger",
        "Spark",
        "Sleep Talk",
        "Encore",
        "Rain Dance",
        "Sunny Day",
        "Uproar",
        "Facade",
        "Charge",
        "Taunt",
        "Helping Hand",
        "Brick Break",
        "Endeavor",
        "Hyper Voice",
        "Metal Sound",
        "Poison Tail",
        "Shock Wave",
        "Fling",
        "Toxic Spikes",
        "Poison Jab",
        "Drain Punch",
        "Giga Impact",
        "Thunder Fang",
        "Discharge",
        "Gunk Shot",
        "Charge Beam",
        "Venoshock",
        "Sludge Wave",
        "Electro Ball",
        "Acid Spray",
        "Stored Power",
        "Hex",
        "Volt Switch",
        "Electroweb",
        "Wild Charge",
        "Snarl",
        "Belch",
        "Noble Roar",
        "Boomburst",
        "Eerie Impulse",
        "Magnetic Flux",
        "Electric Terrain",
        "Nuzzle",
        "Throat Chop",
        "Tearful Look",
        "Overdrive",
        "Tera Blast",
        "Trailblaze",
        "Psychic Noise"
      ],
      "canShiny": true,
      "canAlpha": false,
      "canAlphaShiny": false,
      "canGigantamax": false,
      "levelMax": 75,
      "spriteNormal": "sprites/poke_capture_0849_001_mf_n_00000000_f_n.png",
      "spriteShiny": "sprites/poke_capture_0849_001_mf_n_00000000_f_r.png",
      "spriteGmax": "",
      "spriteShinyGmax": ""
    }
  ]
}