{
  "id": 873,
  "name": "Frosmoth",
  "dexNum": 873,
  "forms": [
    {
      "name": "Frosmoth",
      "formName": "Default Form",
      "formIndex": 0,
      "abilities": [
        "Shield Dust",
        "Ice Scales"
      ],
      "moves": [
        "Take Down",
        "Mist",
        "Ice Beam",
        "Blizzard",
        "Aurora Beam",
        "Hyper Beam",
        "Stun Spore",
        "Light Screen",
        "Reflect",
        "Swift",
        "Leech Life",
        "Rest",
        "Substitute",
        "Powder Snow",
        "Protect",
        "Icy Wind",
        "Giga Drain",
        "Endure",
        "Attract",
        "Sleep Talk",
        "Mirror Coat",
        "Facade",
        "Helping Hand",
        "Imprison",
        "Feather Dance",
        "Weather Ball",
        "Icicle Spear",
        "Calm Mind",
        "Tailwind",
        "U-turn",
        "Air Slash",
        "Bug Buzz",
        "Giga Impact",
        "Avalanche",
        "Defog",
        "Bug Bite",
        "Wide Guard",
        "Quiver Dance",
        "Acrobatics",
        "Struggle Bug",
        "Hurricane",
        "Play Rough",
        "Fairy Wind",
        "Dazzling Gleam",
        "Infestation",
        "Lunge",
        "Aurora Veil",
        "Skitter Smack",
        "Triple Axel",
        "Tera Blast",
        "Ice Spinner",
        "Snowscape",
        "Pounce"
      ],
      "canShiny": true,
      "canAlpha": false,
      "canAlphaShiny": false,
      "canGigantamax": false,
      "levelMax": 75,
      "spriteNormal": "sprites/poke_capture_0873_000_mf_n_00000000_f_n.png",
      "spriteShiny": "sprites/poke_capture_0873_000_mf_n_00000000_f_r.png",
      "spriteGmax": "",
      "spriteShinyGmax": ""
    }
  ]
}