{
  "id": 88,
  "name": "Grimer",
  "dexNum": 88,
  "forms": [
    {
      "name": "Grimer",
      "formName": "Default Form",
      "formIndex": 0,
      "abilities": [
        "Stench",
        "Sticky Hold",
        "Poison Touch"
      ],
      "moves": [
        "Pound",
        "Fire Punch",
        "Ice Punch",
        "Thunder Punch",
        "Body Slam",
        "Take Down",
        "Disable",
        "Flamethrower",
        "Thunderbolt",
        "Thunder",
        "Dig",
        "Toxic",
        "Screech",
        "Harden",
        "Minimize",
        "Confuse Ray",
        "Haze",
        "Metronome",
        "Sludge",
        "Fire Blast",
        "Poison Gas",
        "Acid Armor",
        "Rest",
        "Rock Slide",
        "Substitute",
        "Thief",
        "Curse",
        "Protect",
        "Scary Face",
        "Sludge Bomb",
        "Mud-Slap",
        "Sandstorm",
        "Giga Drain",
        "Endure",
        "Mean Look",
        "Sleep Talk",
        "Pain Split",
        "Rain Dance",
        "Sunny Day",
        "Shadow Ball",
        "Stockpile",
        "Spit Up",
        "Swallow",
        "Memento",
        "Facade",
        "Taunt",
        "Helping Hand",
        "Imprison",
        "Rock Tomb",
        "Shadow Punch",
        "Mud Shot",
        "Fling",
        "Poison Jab",
        "Drain Punch",
        "Shadow Sneak",
        "Zen Headbutt",
        "Gunk Shot",
        "Venoshock",
        "Sludge Wave",
        "Acid Spray",
        "Hex",
        "Belch",
        "Tera Blast"
      ],
      "canShiny": true,
      "canAlpha": false,
      "canAlphaShiny": false,
      "canGigantamax": false,
      "levelMax": 70,
      "spriteNormal": "sprites/poke_capture_0088_000_mf_n_00000000_f_n.png",
      "spriteShiny": "sprites/poke_capture_0088_000_mf_n_00000000_f_r.png",
      "spriteGmax": "",
      "spriteShinyGmax": ""
    },
    {
      "name": "Grimer",
      "formName": "Alola",
      "formIndex": 1,
      "abilities": [
        "Poison Touch",
        "Gluttony",
        "Power of Alchemy"
      ],
      "moves": [
        "Pound",
        "Fire Punch",
        "Ice Punch",
        "Thunder Punch",
        "Body Slam",
        "Take Down",
        "Bite",
        "Disable",
        "Flamethrower",
        "Hyper Beam",
        "Thunderbolt",
        "Thunder",
        "Dig",
        "Toxic",
        "Screech",
        "Harden",
        "Minimize",
        "Metronome",
        "Fire Blast",
        "Swift",
        "Poison Gas",
        "Acid Armor",
        "Rest",
        "Rock Slide",
        "Substitute",
        "Thief",
        "Curse",
        "Spite",
        "Protect",
        "Scary Face",
        "Sludge Bomb",
        "Mud-Slap",
        "Sandstorm",
        "Giga Drain",
        "Endure",
        "Mean Look",
        "Sleep Talk",
        "Pain Split",
        "Rain Dance",
        "Sunny Day",
        "Crunch",
        "Shadow Ball",
        "Stockpile",
        "Spit Up",
        "Swallow",
        "Memento",
        "Facade",
        "Taunt",
        "Helping Hand",
        "Recycle",
        "Brick Break",
        "Knock Off",
        "Imprison",
        "Poison Fang",
        "Rock Tomb",
        "Mud Shot",
        "Assurance",
        "Fling",
        "Poison Jab",
        "Dark Pulse",
        "Drain Punch",
        "Giga Impact",
        "Shadow Sneak",
        "Zen Headbutt",
        "Gunk Shot",
        "Stone Edge",
        "Venoshock",
        "Sludge Wave",
        "Acid Spray",
        "Clear Smog",
        "Hex",
        "Snarl",
        "Belch",
        "Tera Blast"
      ],
      "canShiny": true,
      "canAlpha": false,
      "canAlphaShiny": false,
      "canGigantamax": false,
      "levelMax": 69,
      "spriteNormal": "sprites/poke_capture_0088_001_mf_n_00000000_f_n.png",
      "spriteShiny": "sprites/poke_capture_0088_001_mf_n_00000000_f_r.png",
      "spriteGmax": "",
      "spriteShinyGmax": ""
    }
  ]
}