{
  "id": 892,
  "name": "Urshifu",
  "dexNum": 892,
  "forms": [
    {
      "name": "Urshifu",
      "formName": "Default Form",
      "formIndex": 0,
      "abilities": [
        "Unseen Fist"
      ],
      "moves": [
        "Fire Punch",
        "Ice Punch",
        "Thunder Punch",
        "Swords Dance",
        "Headbutt",
        "Body Slam",
        "Take Down",
        "Double-Edge",
        "Leer",
        "Roar",
        "Low Kick",
        "Counter",
        "Dig",
        "Focus Energy",
        "Swift",
        "Rest",
        "Rock Slide",
        "Substitute",
        "Reversal",
        "Protect",
        "Scary Face",
        "Detect",
        "Endure",
        "False Swipe",
        "Sleep Talk",
        "Dynamic Punch",
        "Metal Claw",
        "Crunch",
        "Rock Smash",
        "Facade",
        "Focus Punch",
        "Taunt",
        "Helping Hand",
        "Brick Break",
        "Rock Tomb",
        "Aerial Ace",
        "Iron Defense",
        "Bulk Up",
        "U-turn",
        "Close Combat",
        "Fling",
        "Sucker Punch",
        "Aura Sphere",
        "Poison Jab",
        "Dark Pulse",
        "Drain Punch",
        "Focus Blast",
        "Giga Impact",
        "Zen Headbutt",
        "Iron Head",
        "Stone Edge",
        "Low Sweep",
        "Foul Play",
        "Acrobatics",
        "Snarl",
        "Throat Chop",
        "Body Press",
        "Lash Out",
        "Coaching",
        "Wicked Blow",
        "Tera Blast",
        "Trailblaze"
      ],
      "canShiny": false,
      "canAlpha": false,
      "canAlphaShiny": false,
      "canGigantamax": false,
      "levelMax": 50,
      "spriteNormal": "sprites/poke_capture_0892_000_mf_n_00000000_f_n.png",
      "spriteShiny": "",
      "spriteGmax": "",
      "spriteShinyGmax": ""
    },
    {
      "name": "Urshifu",
      "formName": "Rapid Strike",
      "formIndex": 1,
      "abilities": [
        "Unseen Fist"
      ],
      "moves": [
        "Fire Punch",
        "Ice Punch",
        "Thunder Punch",
        "Swords Dance",
        "Headbutt",
        "Body Slam",
        "Take Down",
        "Double-Edge",
        "Leer",
        "Low Kick",
        "Counter",
        "Dig",
        "Focus Energy",
        "Waterfall",
        "Swift",
        "Rest",
        "Rock Slide",
        "Substitute",
        "Reversal",
        "Protect",
        "Scary Face",
        "Detect",
        "Endure",
        "False Swipe",
        "Sleep Talk",
        "Dynamic Punch",
        "Metal Claw",
        "Rain Dance",
        "Rock Smash",
        "Whirlpool",
        "Facade",
        "Focus Punch",
        "Taunt",
        "Helping Hand",
        "Brick Break",
        "Rock Tomb",
        "Aerial Ace",
        "Iron Defense",
        "Bulk Up",
        "U-turn",
        "Close Combat",
        "Fling",
        "Aura Sphere",
        "Poison Jab",
        "Drain Punch",
        "Focus Blast",
        "Giga Impact",
        "Zen Headbutt",
        "Iron Head",
        "Stone Edge",
        "Aqua Jet",
        "Low Sweep",
        "Acrobatics",
        "Liquidation",
        "Body Press",
        "Coaching",
        "Surging Strikes",
        "Tera Blast",
        "Ice Spinner",
        "Trailblaze",
        "Chilling Water"
      ],
      "canShiny": false,
      "canAlpha": false,
      "canAlphaShiny": false,
      "canGigantamax": false,
      "levelMax": 50,
      "spriteNormal": "sprites/poke_capture_0892_001_mf_n_00000000_f_n.png",
      "spriteShiny": "",
      "spriteGmax": "",
      "spriteShinyGmax": ""
    }
  ]
}