{
  "id": 923,
  "name": "Pawmot",
  "dexNum": 923,
  "forms": [
    {
      "name": "Pawmot",
      "formName": "Default Form",
      "formIndex": 0,
      "abilities": [
        "Volt Absorb",
        "Natural Cure",
        "Iron Fist"
      ],
      "moves": [
        "Fire Punch",
        "Ice Punch",
        "Thunder Punch",
        "Scratch",
        "Slam",
        "Take Down",
        "Double-Edge",
        "Bite",
        "Growl",
        "Hyper Beam",
        "Low Kick",
        "Thunder Shock",
        "Thunderbolt",
        "Thunder Wave",
        "Thunder",
        "Dig",
        "Agility",
        "Quick Attack",
        "Metronome",
        "Swift",
        "Rest",
        "Super Fang",
        "Substitute",
        "Thief",
        "Protect",
        "Mach Punch",
        "Sweet Kiss",
        "Endure",
        "Charm",
        "Spark",
        "Sleep Talk",
        "Baton Pass",
        "Encore",
        "Metal Claw",
        "Rain Dance",
        "Sunny Day",
        "Crunch",
        "Fake Out",
        "Facade",
        "Focus Punch",
        "Charge",
        "Helping Hand",
        "Wish",
        "Brick Break",
        "Knock Off",
        "Arm Thrust",
        "Rock Tomb",
        "Bulk Up",
        "Close Combat",
        "Fling",
        "Seed Bomb",
        "Focus Blast",
        "Giga Impact",
        "Thunder Fang",
        "Discharge",
        "Grass Knot",
        "Charge Beam",
        "Electro Ball",
        "Low Sweep",
        "Entrainment",
        "Volt Switch",
        "Electroweb",
        "Wild Charge",
        "Play Rough",
        "Eerie Impulse",
        "Electric Terrain",
        "Nuzzle",
        "Throat Chop",
        "Body Press",
        "Coaching",
        "Tera Blast",
        "Revival Blessing",
        "Double Shock",
        "Supercell Slam",
        "Upper Hand"
      ],
      "canShiny": true,
      "canAlpha": false,
      "canAlphaShiny": false,
      "canGigantamax": false,
      "levelMax": 75,
      "spriteNormal": "sprites/poke_capture_0923_000_mf_n_00000000_f_n.png",
      "spriteShiny": "sprites/poke_capture_0923_000_mf_n_00000000_f_r.png",
      "spriteGmax": "",
      "spriteShinyGmax": ""
    }
  ]
}