{
  "id": 259,
  "name": "Marshtomp",
  "dexNum": 259,
  "forms": [
    {
      "name": "Marshtomp",
      "formName": "Default Form",
      "formIndex": 0,
      "abilities": [
        "Torrent",
        "Damp"
      ],
      "moves": [
        "Ice Punch",
        "Tackle",
        "Body Slam",
        "Take Down",
        "Double-Edge",
        "Bite",
        "Growl",
        "Roar",
        "Supersonic",
        "Water Gun",
        "Hydro Pump",
        "Surf",
        "Ice Beam",
        "Blizzard",
        "Bubble Beam",
        "Rock Throw",
        "Earthquake",
        "Dig",
        "Screech",
        "Waterfall",
        "Amnesia",
        "Rock Slide",
        "Substitute",
        "Curse",
        "Protect",
        "Sludge Bomb",
        "Icy Wind",
        "Endure",
        "Iron Tail",
        "Ancient Power",
        "Rock Smash",
        "Whirlpool",
        "Facade",
        "Brick Break",
        "Rock Tomb",
        "Sand Tomb",
        "Muddy Water",
        "Mud Shot",
        "Water Pulse",
        "Aqua Ring",
        "Earth Power",
        "Stealth Rock",
        "Scald",
        "Bulldoze",
        "Work Up",
        "Liquidation",
        "Chilling Water"
      ],
      "canShiny": true,
      "canAlpha": true,
      "canAlphaShiny": true,
      "canGigantamax": false,
      "levelMax": 61,
      "spriteNormal": "sprites/poke_capture_0259_000_mf_n_00000000_f_n.png",
      "spriteShiny": "sprites/poke_capture_0259_000_mf_n_00000000_f_r.png",
      "spriteGmax": "",
      "spriteShinyGmax": ""
    }
  ]
}